ninjecto/__init__.py
ninjecto/__main__.py
ninjecto/args.py
ninjecto/config.py
ninjecto/core.py
ninjecto/inputs.py
ninjecto/local.py
ninjecto/values.py
ninjecto/data/config.yaml
ninjecto/plugins/__init__.py
ninjecto/plugins/loader.py
ninjecto/plugins/filters/__init__.py
ninjecto/plugins/filters/comment.py
ninjecto/plugins/filters/quote.py
ninjecto/plugins/filters/read.py
ninjecto/plugins/namespaces/__init__.py
ninjecto/plugins/namespaces/env.py
ninjecto/plugins/namespaces/git.py
ninjecto/plugins/namespaces/vault.py
ninjecto/utils/__init__.py
ninjecto/utils/command.py
ninjecto/utils/dictionary.py
ninjecto/utils/git.py
ninjecto/utils/iso8601.py
ninjecto/utils/types.py
ninjecto-1.1.0.dist-info/licenses/LICENSE
ninjecto-1.1.0.dist-info/METADATA
ninjecto-1.1.0.dist-info/WHEEL
ninjecto-1.1.0.dist-info/entry_points.txt
ninjecto-1.1.0.dist-info/top_level.txt
ninjecto-1.1.0.dist-info/RECORD
