Metadata-Version: 2.4
Name: ninjecto
Version: 1.1.0
Summary: Ninja Injection Tool. Template rendering and variable injection made easy.
Author-email: "KuraLabs S.R.L" <info@kuralabs.io>
License: Apache-2.0
Project-URL: Homepage, https://github.com/kuralabs/ninjecto
Keywords: ninjecto
Classifier: Development Status :: 5 - Production/Stable
Classifier: Intended Audience :: Developers
Classifier: Natural Language :: English
Classifier: Operating System :: POSIX :: Linux
Classifier: Programming Language :: Python :: 3
Requires-Python: >=3.8
License-File: LICENSE
Requires-Dist: toml
Requires-Dist: ujson
Requires-Dist: pyyaml
Requires-Dist: jinja2>=3.1.0
Requires-Dist: inflection
Requires-Dist: packagedata
Requires-Dist: colorlog
Requires-Dist: pprintpp
Requires-Dist: setproctitle
Provides-Extra: vault
Requires-Dist: hvac; extra == "vault"
Dynamic: license-file
